LICENSE
MANIFEST.in
README.md
setup.py
maxatac/__init__.py
maxatac/git_version
maxatac.egg-info/PKG-INFO
maxatac.egg-info/SOURCES.txt
maxatac.egg-info/dependency_links.txt
maxatac.egg-info/not-zip-safe
maxatac.egg-info/requires.txt
maxatac.egg-info/top_level.txt
maxatac/analyses/__init__.py
maxatac/analyses/average.py
maxatac/analyses/benchmark.py
maxatac/analyses/data.py
maxatac/analyses/normalize.py
maxatac/analyses/peaks.py
maxatac/analyses/predict.py
maxatac/analyses/prepare.py
maxatac/analyses/threshold.py
maxatac/analyses/train.py
maxatac/analyses/variants.py
maxatac/architectures/__init__.py
maxatac/architectures/dcnn.py
maxatac/bin/__init__.py
maxatac/bin/maxatac
maxatac/utilities/__init__.py
maxatac/utilities/benchmarking_tools.py
maxatac/utilities/callbacks.py
maxatac/utilities/constants.py
maxatac/utilities/genome_tools.py
maxatac/utilities/logger.py
maxatac/utilities/normalization_tools.py
maxatac/utilities/parser.py
maxatac/utilities/peak_tools.py
maxatac/utilities/plot.py
maxatac/utilities/prediction_tools.py
maxatac/utilities/prepare_tools.py
maxatac/utilities/system_tools.py
maxatac/utilities/threshold_tools.py
maxatac/utilities/training_tools.py
maxatac/utilities/variant_tools.py
tests/test_data.py
tests/test_helpers.py
tests/test_parser.py
tests/test_tools.py