Metadata-Version: 2.1
Name: maxatac
Version: 1.0.6
Summary: maxATAC: a suite of user-friendly, deep neural network models for transcription factor binding prediction from ATAC-seq
Home-page: https://github.com/MiraldiLab/maxATAC
Download-URL: https://github.com/MiraldiLab/maxATAC
Author: Tareian, Faiz
Author-email: tacazares@gmail.com, faizrizvi1993@gmail.com
License: Apache-2.0
License-File: LICENSE
Requires-Dist: tensorflow
Requires-Dist: tensorboard
Requires-Dist: biopython
Requires-Dist: py2bit
Requires-Dist: pyBigWig
Requires-Dist: pydot
Requires-Dist: matplotlib
Requires-Dist: scikit-learn
Requires-Dist: pybedtools
Requires-Dist: pandas
Requires-Dist: pyfiglet
Requires-Dist: pyyaml
Requires-Dist: pysam
Requires-Dist: seaborn
Requires-Dist: pytest
